[
    {
        "key": "dbln",
        "value": "%7B%2261582672011725%22%3A%22IolQtke6%22%7D",
        "domain": "facebook.com",
        "path": "/login/device-based/",
        "hostOnly": false,
        "creation": "2025-10-25T11:15:15.331Z",
        "lastAccessed": "2025-10-25T11:15:15.331Z"
    },
    {
        "key": "datr",
        "value": "mSz8aF4SJjc995nKdzfHyb7o",
        "domain": "facebook.com",
        "path": "/",
        "hostOnly": false,
        "creation": "2025-10-25T11:15:15.331Z",
        "lastAccessed": "2025-10-25T11:15:15.331Z"
    },
    {
        "key": "ps_l",
        "value": "1",
        "domain": "facebook.com",
        "path": "/",
        "hostOnly": false,
        "creation": "2025-10-25T11:15:15.331Z",
        "lastAccessed": "2025-10-25T11:15:15.331Z"
    },
    {
        "key": "ps_n",
        "value": "1",
        "domain": "facebook.com",
        "path": "/",
        "hostOnly": false,
        "creation": "2025-10-25T11:15:15.331Z",
        "lastAccessed": "2025-10-25T11:15:15.331Z"
    },
    {
        "key": "sb",
        "value": "mSz8aLUotD2Owgx3oVrBcJmF",
        "domain": "facebook.com",
        "path": "/",
        "hostOnly": false,
        "creation": "2025-10-25T11:15:15.331Z",
        "lastAccessed": "2025-10-25T11:15:15.331Z"
    },
    {
        "key": "vpd",
        "value": "v1%3B736x393x2.75",
        "domain": "facebook.com",
        "path": "/",
        "hostOnly": false,
        "creation": "2025-10-25T11:15:15.331Z",
        "lastAccessed": "2025-10-25T11:15:15.331Z"
    },
    {
        "key": "c_user",
        "value": "61582672011725",
        "domain": "facebook.com",
        "path": "/",
        "hostOnly": false,
        "creation": "2025-10-25T11:15:15.331Z",
        "lastAccessed": "2025-10-25T11:15:15.331Z"
    },
    {
        "key": "xs",
        "value": "39%3At74bePQbfBOZXA%3A2%3A1761367303%3A-1%3A-1",
        "domain": "facebook.com",
        "path": "/",
        "hostOnly": false,
        "creation": "2025-10-25T11:15:15.331Z",
        "lastAccessed": "2025-10-25T11:15:15.331Z"
    },
    {
        "key": "locale",
        "value": "en_GB",
        "domain": "facebook.com",
        "path": "/",
        "hostOnly": false,
        "creation": "2025-10-25T11:15:15.331Z",
        "lastAccessed": "2025-10-25T11:15:15.331Z"
    },
    {
        "key": "pas",
        "value": "61582561050365%3AWvFCBVVRYb%2C61582672011725%3A3KI2a9wWyO",
        "domain": "facebook.com",
        "path": "/",
        "hostOnly": false,
        "creation": "2025-10-25T11:15:15.331Z",
        "lastAccessed": "2025-10-25T11:15:15.331Z"
    },
    {
        "key": "fr",
        "value": "03D0ghUB1SxJbFr2a.AWf2spr8EzT75zRElVU7t7-WY3DvDiXk_T29WRXT32-LsqXeSH0.Bo_CyZ..AAA.0.0.Bo_LFA.AWdYoRB0sGM2EOsgb2By9CeMnvs",
        "domain": "facebook.com",
        "path": "/",
        "hostOnly": false,
        "creation": "2025-10-25T11:15:15.331Z",
        "lastAccessed": "2025-10-25T11:15:15.331Z"
    },
    {
        "key": "wl_cbv",
        "value": "v2%3Bclient_version%3A2964%3Btimestamp%3A1761390912",
        "domain": "facebook.com",
        "path": "/",
        "hostOnly": false,
        "creation": "2025-10-25T11:15:15.331Z",
        "lastAccessed": "2025-10-25T11:15:15.331Z"
    },
    {
        "key": "fbl_st",
        "value": "100429588%3BT%3A29356515",
        "domain": "facebook.com",
        "path": "/",
        "hostOnly": false,
        "creation": "2025-10-25T11:15:15.331Z",
        "lastAccessed": "2025-10-25T11:15:15.331Z"
    }
]
